<anim ver="netanim-3.108" filetype="animation" >
<node id="0" sysId="0" locX="48" locY="30" />
<node id="1" sysId="0" locX="36.11531119" locY="70.78770829" />
<node id="2" sysId="0" locX="65.49207691" locY="75.16930957" />
<node id="3" sysId="0" locX="45" locY="52" />
<node id="4" sysId="0" locX="48" locY="50" />
<node id="5" sysId="0" locX="49.33255445" locY="65.65484422" />
<node id="6" sysId="0" locX="52.74634324" locY="45.48607834" />
<node id="7" sysId="0" locX="64.10944256" locY="49.77639831" />
<node id="8" sysId="0" locX="86.16274451" locY="58.97088335" />
<node id="9" sysId="0" locX="104.4571933" locY="47.03087658" />
<node id="10" sysId="0" locX="77.67566506" locY="55.04473523" />
<node id="11" sysId="0" locX="86.73111955" locY="52.42192698" />
<node id="12" sysId="0" locX="79.77460094" locY="72.81013787" />
<node id="13" sysId="0" locX="80.8496915" locY="43.0967815" />
<node id="14" sysId="0" locX="87.36614674" locY="60.66027176" />
<node id="15" sysId="0" locX="84.96217832" locY="57.75849453" />
<node id="16" sysId="0" locX="53.13499313" locY="48.62582718" />
<node id="17" sysId="0" locX="56.93367873" locY="77.88399856" />
<node id="18" sysId="0" locX="37.49010777" locY="59.13914065" />
<node id="19" sysId="0" locX="53.65221246" locY="66.93816278" />
<node id="20" sysId="0" locX="51.71950645" locY="62.66547513" />
<node id="21" sysId="0" locX="62.89610537" locY="51.47130704" />
<node id="22" sysId="0" locX="47.13124954" locY="63.66798697" />
<node id="23" sysId="0" locX="54.85262147" locY="81.85765016" />
<node id="24" sysId="0" locX="50" locY="70" />
<node id="25" sysId="0" locX="100" locY="70" />
<node id="26" sysId="0" locX="70" locY="70" />
<node id="27" sysId="0" locX="85" locY="75" />
<node id="28" sysId="0" locX="75" locY="75" />
<nu p="c" t="0" id="0" r="255" g="0" b="0" />
<nu p="c" t="0" id="1" r="255" g="0" b="0" />
<nu p="c" t="0" id="2" r="255" g="0" b="0" />
<nu p="c" t="0" id="3" r="255" g="0" b="0" />
<nu p="c" t="0" id="4" r="255" g="0" b="0" />
<nu p="c" t="0" id="5" r="255" g="0" b="0" />
<nu p="c" t="0" id="6" r="255" g="0" b="0" />
<nu p="c" t="0" id="7" r="255" g="0" b="0" />
<nu p="c" t="0" id="8" r="255" g="0" b="0" />
<nu p="c" t="0" id="9" r="255" g="0" b="0" />
<nu p="c" t="0" id="10" r="255" g="0" b="0" />
<nu p="c" t="0" id="11" r="255" g="0" b="0" />
<nu p="c" t="0" id="12" r="255" g="0" b="0" />
<nu p="c" t="0" id="13" r="255" g="0" b="0" />
<nu p="c" t="0" id="14" r="255" g="0" b="0" />
<nu p="c" t="0" id="15" r="255" g="0" b="0" />
<nu p="c" t="0" id="16" r="255" g="0" b="0" />
<nu p="c" t="0" id="17" r="255" g="0" b="0" />
<nu p="c" t="0" id="18" r="255" g="0" b="0" />
<nu p="c" t="0" id="19" r="255" g="0" b="0" />
<nu p="c" t="0" id="20" r="255" g="0" b="0" />
<nu p="c" t="0" id="21" r="255" g="0" b="0" />
<nu p="c" t="0" id="22" r="255" g="0" b="0" />
<nu p="c" t="0" id="23" r="255" g="0" b="0" />
<nu p="c" t="0" id="24" r="255" g="0" b="0" />
<nu p="c" t="0" id="25" r="255" g="0" b="0" />
<nu p="c" t="0" id="26" r="255" g="0" b="0" />
<nu p="c" t="0" id="27" r="255" g="0" b="0" />
<nu p="c" t="0" id="28" r="255" g="0" b="0" />
<nonp2plinkproperties id="0" ipAddress="10.1.1.1~00:00:00:00:00:00:00:03" channelType="Unknown channel" />
<nonp2plinkproperties id="0" ipAddress="10.1.1.1~00:00:00:00:00:00:00:03" channelType="Unknown channel" />
<nonp2plinkproperties id="0" ipAddress="127.0.0.1~00:00:00:00:00:00" channelType="Unknown channel" />
<nonp2plinkproperties id="1" ipAddress="10.1.1.2~00:00:00:00:00:00:00:04" channelType="Unknown channel" />
<nonp2plinkproperties id="1" ipAddress="10.1.1.2~00:00:00:00:00:00:00:04" channelType="Unknown channel" />
<nonp2plinkproperties id="1" ipAddress="127.0.0.1~00:00:00:00:00:00" channelType="Unknown channel" />
<nonp2plinkproperties id="2" ipAddress="10.1.1.3~00:00:00:00:00:00:00:05" channelType="Unknown channel" />
<nonp2plinkproperties id="2" ipAddress="10.1.1.3~00:00:00:00:00:00:00:05" channelType="Unknown channel" />
<nonp2plinkproperties id="2" ipAddress="127.0.0.1~00:00:00:00:00:00" channelType="Unknown channel" />
<nonp2plinkproperties id="3" ipAddress="10.1.1.4~00:00:00:00:00:00:00:06" channelType="Unknown channel" />
<nonp2plinkproperties id="3" ipAddress="10.1.1.4~00:00:00:00:00:00:00:06" channelType="Unknown channel" />
<nonp2plinkproperties id="3" ipAddress="127.0.0.1~00:00:00:00:00:00" channelType="Unknown channel" />
<nonp2plinkproperties id="4" ipAddress="10.1.1.5~00:00:00:00:00:00:00:07" channelType="Unknown channel" />
<nonp2plinkproperties id="4" ipAddress="10.1.1.5~00:00:00:00:00:00:00:07" channelType="Unknown channel" />
<nonp2plinkproperties id="4" ipAddress="127.0.0.1~00:00:00:00:00:00" channelType="Unknown channel" />
<nonp2plinkproperties id="5" ipAddress="10.1.1.6~00:00:00:00:00:00:00:08" channelType="Unknown channel" />
<nonp2plinkproperties id="5" ipAddress="10.1.1.6~00:00:00:00:00:00:00:08" channelType="Unknown channel" />
<nonp2plinkproperties id="5" ipAddress="127.0.0.1~00:00:00:00:00:00" channelType="Unknown channel" />
<nonp2plinkproperties id="6" ipAddress="10.1.1.7~00:00:00:00:00:00:00:09" channelType="Unknown channel" />
<nonp2plinkproperties id="6" ipAddress="10.1.1.7~00:00:00:00:00:00:00:09" channelType="Unknown channel" />
<nonp2plinkproperties id="6" ipAddress="127.0.0.1~00:00:00:00:00:00" channelType="Unknown channel" />
<nonp2plinkproperties id="7" ipAddress="10.1.1.8~00:00:00:00:00:00:00:0a" channelType="Unknown channel" />
<nonp2plinkproperties id="7" ipAddress="10.1.1.8~00:00:00:00:00:00:00:0a" channelType="Unknown channel" />
<nonp2plinkproperties id="7" ipAddress="127.0.0.1~00:00:00:00:00:00" channelType="Unknown channel" />
<nonp2plinkproperties id="8" ipAddress="10.1.1.9~00:00:00:00:00:00:00:0b" channelType="Unknown channel" />
<nonp2plinkproperties id="8" ipAddress="10.1.1.9~00:00:00:00:00:00:00:0b" channelType="Unknown channel" />
<nonp2plinkproperties id="8" ipAddress="127.0.0.1~00:00:00:00:00:00" channelType="Unknown channel" />
<nonp2plinkproperties id="9" ipAddress="10.1.1.10~00:00:00:00:00:00:00:0c" channelType="Unknown channel" />
<nonp2plinkproperties id="9" ipAddress="10.1.1.10~00:00:00:00:00:00:00:0c" channelType="Unknown channel" />
<nonp2plinkproperties id="9" ipAddress="127.0.0.1~00:00:00:00:00:00" channelType="Unknown channel" />
<nonp2plinkproperties id="10" ipAddress="10.1.1.11~00:00:00:00:00:00:00:0d" channelType="Unknown channel" />
<nonp2plinkproperties id="10" ipAddress="10.1.1.11~00:00:00:00:00:00:00:0d" channelType="Unknown channel" />
<nonp2plinkproperties id="10" ipAddress="127.0.0.1~00:00:00:00:00:00" channelType="Unknown channel" />
<nonp2plinkproperties id="11" ipAddress="10.1.1.12~00:00:00:00:00:00:00:0e" channelType="Unknown channel" />
<nonp2plinkproperties id="11" ipAddress="10.1.1.12~00:00:00:00:00:00:00:0e" channelType="Unknown channel" />
<nonp2plinkproperties id="11" ipAddress="127.0.0.1~00:00:00:00:00:00" channelType="Unknown channel" />
<nonp2plinkproperties id="12" ipAddress="10.1.1.13~00:00:00:00:00:00:00:0f" channelType="Unknown channel" />
<nonp2plinkproperties id="12" ipAddress="10.1.1.13~00:00:00:00:00:00:00:0f" channelType="Unknown channel" />
<nonp2plinkproperties id="12" ipAddress="127.0.0.1~00:00:00:00:00:00" channelType="Unknown channel" />
<nonp2plinkproperties id="13" ipAddress="10.1.1.14~00:00:00:00:00:00:00:10" channelType="Unknown channel" />
<nonp2plinkproperties id="13" ipAddress="10.1.1.14~00:00:00:00:00:00:00:10" channelType="Unknown channel" />
<nonp2plinkproperties id="13" ipAddress="127.0.0.1~00:00:00:00:00:00" channelType="Unknown channel" />
<nonp2plinkproperties id="14" ipAddress="10.1.1.15~00:00:00:00:00:00:00:11" channelType="Unknown channel" />
<nonp2plinkproperties id="14" ipAddress="10.1.1.15~00:00:00:00:00:00:00:11" channelType="Unknown channel" />
<nonp2plinkproperties id="14" ipAddress="127.0.0.1~00:00:00:00:00:00" channelType="Unknown channel" />
<nonp2plinkproperties id="15" ipAddress="10.1.1.16~00:00:00:00:00:00:00:12" channelType="Unknown channel" />
<nonp2plinkproperties id="15" ipAddress="10.1.1.16~00:00:00:00:00:00:00:12" channelType="Unknown channel" />
<nonp2plinkproperties id="15" ipAddress="127.0.0.1~00:00:00:00:00:00" channelType="Unknown channel" />
<nonp2plinkproperties id="16" ipAddress="10.1.1.17~00:00:00:00:00:00:00:13" channelType="Unknown channel" />
<nonp2plinkproperties id="16" ipAddress="10.1.1.17~00:00:00:00:00:00:00:13" channelType="Unknown channel" />
<nonp2plinkproperties id="16" ipAddress="127.0.0.1~00:00:00:00:00:00" channelType="Unknown channel" />
<nonp2plinkproperties id="17" ipAddress="10.1.1.18~00:00:00:00:00:00:00:14" channelType="Unknown channel" />
<nonp2plinkproperties id="17" ipAddress="10.1.1.18~00:00:00:00:00:00:00:14" channelType="Unknown channel" />
<nonp2plinkproperties id="17" ipAddress="127.0.0.1~00:00:00:00:00:00" channelType="Unknown channel" />
<nonp2plinkproperties id="18" ipAddress="10.1.1.19~00:00:00:00:00:00:00:15" channelType="Unknown channel" />
<nonp2plinkproperties id="18" ipAddress="10.1.1.19~00:00:00:00:00:00:00:15" channelType="Unknown channel" />
<nonp2plinkproperties id="18" ipAddress="127.0.0.1~00:00:00:00:00:00" channelType="Unknown channel" />
<nonp2plinkproperties id="19" ipAddress="10.1.1.20~00:00:00:00:00:00:00:16" channelType="Unknown channel" />
<nonp2plinkproperties id="19" ipAddress="10.1.1.20~00:00:00:00:00:00:00:16" channelType="Unknown channel" />
<nonp2plinkproperties id="19" ipAddress="127.0.0.1~00:00:00:00:00:00" channelType="Unknown channel" />
<nonp2plinkproperties id="20" ipAddress="10.1.1.21~00:00:00:00:00:00:00:17" channelType="Unknown channel" />
<nonp2plinkproperties id="20" ipAddress="10.1.1.21~00:00:00:00:00:00:00:17" channelType="Unknown channel" />
<nonp2plinkproperties id="20" ipAddress="127.0.0.1~00:00:00:00:00:00" channelType="Unknown channel" />
<nonp2plinkproperties id="21" ipAddress="10.1.1.22~00:00:00:00:00:00:00:18" channelType="Unknown channel" />
<nonp2plinkproperties id="21" ipAddress="10.1.1.22~00:00:00:00:00:00:00:18" channelType="Unknown channel" />
<nonp2plinkproperties id="21" ipAddress="127.0.0.1~00:00:00:00:00:00" channelType="Unknown channel" />
<nonp2plinkproperties id="22" ipAddress="10.1.1.23~00:00:00:00:00:00:00:19" channelType="Unknown channel" />
<nonp2plinkproperties id="22" ipAddress="10.1.1.23~00:00:00:00:00:00:00:19" channelType="Unknown channel" />
<nonp2plinkproperties id="22" ipAddress="127.0.0.1~00:00:00:00:00:00" channelType="Unknown channel" />
<nonp2plinkproperties id="23" ipAddress="10.1.1.24~00:00:00:00:00:00:00:1a" channelType="Unknown channel" />
<nonp2plinkproperties id="23" ipAddress="10.1.1.24~00:00:00:00:00:00:00:1a" channelType="Unknown channel" />
<nonp2plinkproperties id="23" ipAddress="127.0.0.1~00:00:00:00:00:00" channelType="Unknown channel" />
<nonp2plinkproperties id="24" ipAddress="127.0.0.1~00:00:00:00:00:00" channelType="Unknown channel" />
<link fromId="24" toId="26" fd="10.0.0.5~00:00:00:00:00:02" td="10.0.0.6~00:00:00:00:00:03" ld="" />
<link fromId="24" toId="27" fd="11.0.0.5~00:00:00:00:00:04" td="11.0.0.6~00:00:00:00:00:05" ld="" />
<nonp2plinkproperties id="25" ipAddress="127.0.0.1~00:00:00:00:00:00" channelType="Unknown channel" />
<link fromId="25" toId="26" fd="10.0.0.9~00:00:00:00:00:06" td="10.0.0.10~00:00:00:00:00:07" ld="" />
<link fromId="25" toId="27" fd="11.0.0.9~00:00:00:00:00:08" td="11.0.0.10~00:00:00:00:00:09" ld="" />
<nonp2plinkproperties id="26" ipAddress="127.0.0.1~00:00:00:00:00:00" channelType="Unknown channel" />
<nonp2plinkproperties id="26" ipAddress="7.0.0.1~00:00:00:00:00:01" channelType="Unknown channel" />
<link fromId="26" toId="28" fd="1.0.0.1~00:00:00:00:00:0a" td="1.0.0.2~00:00:00:00:00:0b" ld="" />
<nonp2plinkproperties id="27" ipAddress="127.0.0.1~00:00:00:00:00:00" channelType="Unknown channel" />
<nonp2plinkproperties id="28" ipAddress="127.0.0.1~00:00:00:00:00:00" channelType="Unknown channel" />
<ip n="0" >
<address >10.1.1.1</address>

<address >10.1.1.1</address>

<address >127.0.0.1</address>

</ip>
<ip n="0" >
<address >10.1.1.1</address>

<address >10.1.1.1</address>

<address >127.0.0.1</address>

</ip>
<ip n="0" >
<address >10.1.1.1</address>

<address >10.1.1.1</address>

<address >127.0.0.1</address>

</ip>
<ip n="1" >
<address >10.1.1.2</address>

<address >10.1.1.2</address>

<address >127.0.0.1</address>

</ip>
<ip n="1" >
<address >10.1.1.2</address>

<address >10.1.1.2</address>

<address >127.0.0.1</address>

</ip>
<ip n="1" >
<address >10.1.1.2</address>

<address >10.1.1.2</address>

<address >127.0.0.1</address>

</ip>
<ip n="2" >
<address >10.1.1.3</address>

<address >10.1.1.3</address>

<address >127.0.0.1</address>

</ip>
<ip n="2" >
<address >10.1.1.3</address>

<address >10.1.1.3</address>

<address >127.0.0.1</address>

</ip>
<ip n="2" >
<address >10.1.1.3</address>

<address >10.1.1.3</address>

<address >127.0.0.1</address>

</ip>
<ip n="3" >
<address >10.1.1.4</address>

<address >10.1.1.4</address>

<address >127.0.0.1</address>

</ip>
<ip n="3" >
<address >10.1.1.4</address>

<address >10.1.1.4</address>

<address >127.0.0.1</address>

</ip>
<ip n="3" >
<address >10.1.1.4</address>

<address >10.1.1.4</address>

<address >127.0.0.1</address>

</ip>
<ip n="4" >
<address >10.1.1.5</address>

<address >10.1.1.5</address>

<address >127.0.0.1</address>

</ip>
<ip n="4" >
<address >10.1.1.5</address>

<address >10.1.1.5</address>

<address >127.0.0.1</address>

</ip>
<ip n="4" >
<address >10.1.1.5</address>

<address >10.1.1.5</address>

<address >127.0.0.1</address>

</ip>
<ip n="5" >
<address >10.1.1.6</address>

<address >10.1.1.6</address>

<address >127.0.0.1</address>

</ip>
<ip n="5" >
<address >10.1.1.6</address>

<address >10.1.1.6</address>

<address >127.0.0.1</address>

</ip>
<ip n="5" >
<address >10.1.1.6</address>

<address >10.1.1.6</address>

<address >127.0.0.1</address>

</ip>
<ip n="6" >
<address >10.1.1.7</address>

<address >10.1.1.7</address>

<address >127.0.0.1</address>

</ip>
<ip n="6" >
<address >10.1.1.7</address>

<address >10.1.1.7</address>

<address >127.0.0.1</address>

</ip>
<ip n="6" >
<address >10.1.1.7</address>

<address >10.1.1.7</address>

<address >127.0.0.1</address>

</ip>
<ip n="7" >
<address >10.1.1.8</address>

<address >10.1.1.8</address>

<address >127.0.0.1</address>

</ip>
<ip n="7" >
<address >10.1.1.8</address>

<address >10.1.1.8</address>

<address >127.0.0.1</address>

</ip>
<ip n="7" >
<address >10.1.1.8</address>

<address >10.1.1.8</address>

<address >127.0.0.1</address>

</ip>
<ip n="8" >
<address >10.1.1.9</address>

<address >10.1.1.9</address>

<address >127.0.0.1</address>

</ip>
<ip n="8" >
<address >10.1.1.9</address>

<address >10.1.1.9</address>

<address >127.0.0.1</address>

</ip>
<ip n="8" >
<address >10.1.1.9</address>

<address >10.1.1.9</address>

<address >127.0.0.1</address>

</ip>
<ip n="9" >
<address >10.1.1.10</address>

<address >10.1.1.10</address>

<address >127.0.0.1</address>

</ip>
<ip n="9" >
<address >10.1.1.10</address>

<address >10.1.1.10</address>

<address >127.0.0.1</address>

</ip>
<ip n="9" >
<address >10.1.1.10</address>

<address >10.1.1.10</address>

<address >127.0.0.1</address>

</ip>
<ip n="10" >
<address >10.1.1.11</address>

<address >10.1.1.11</address>

<address >127.0.0.1</address>

</ip>
<ip n="10" >
<address >10.1.1.11</address>

<address >10.1.1.11</address>

<address >127.0.0.1</address>

</ip>
<ip n="10" >
<address >10.1.1.11</address>

<address >10.1.1.11</address>

<address >127.0.0.1</address>

</ip>
<ip n="11" >
<address >10.1.1.12</address>

<address >10.1.1.12</address>

<address >127.0.0.1</address>

</ip>
<ip n="11" >
<address >10.1.1.12</address>

<address >10.1.1.12</address>

<address >127.0.0.1</address>

</ip>
<ip n="11" >
<address >10.1.1.12</address>

<address >10.1.1.12</address>

<address >127.0.0.1</address>

</ip>
<ip n="12" >
<address >10.1.1.13</address>

<address >10.1.1.13</address>

<address >127.0.0.1</address>

</ip>
<ip n="12" >
<address >10.1.1.13</address>

<address >10.1.1.13</address>

<address >127.0.0.1</address>

</ip>
<ip n="12" >
<address >10.1.1.13</address>

<address >10.1.1.13</address>

<address >127.0.0.1</address>

</ip>
<ip n="13" >
<address >10.1.1.14</address>

<address >10.1.1.14</address>

<address >127.0.0.1</address>

</ip>
<ip n="13" >
<address >10.1.1.14</address>

<address >10.1.1.14</address>

<address >127.0.0.1</address>

</ip>
<ip n="13" >
<address >10.1.1.14</address>

<address >10.1.1.14</address>

<address >127.0.0.1</address>

</ip>
<ip n="14" >
<address >10.1.1.15</address>

<address >10.1.1.15</address>

<address >127.0.0.1</address>

</ip>
<ip n="14" >
<address >10.1.1.15</address>

<address >10.1.1.15</address>

<address >127.0.0.1</address>

</ip>
<ip n="14" >
<address >10.1.1.15</address>

<address >10.1.1.15</address>

<address >127.0.0.1</address>

</ip>
<ip n="15" >
<address >10.1.1.16</address>

<address >10.1.1.16</address>

<address >127.0.0.1</address>

</ip>
<ip n="15" >
<address >10.1.1.16</address>

<address >10.1.1.16</address>

<address >127.0.0.1</address>

</ip>
<ip n="15" >
<address >10.1.1.16</address>

<address >10.1.1.16</address>

<address >127.0.0.1</address>

</ip>
<ip n="16" >
<address >10.1.1.17</address>

<address >10.1.1.17</address>

<address >127.0.0.1</address>

</ip>
<ip n="16" >
<address >10.1.1.17</address>

<address >10.1.1.17</address>

<address >127.0.0.1</address>

</ip>
<ip n="16" >
<address >10.1.1.17</address>

<address >10.1.1.17</address>

<address >127.0.0.1</address>

</ip>
<ip n="17" >
<address >10.1.1.18</address>

<address >10.1.1.18</address>

<address >127.0.0.1</address>

</ip>
<ip n="17" >
<address >10.1.1.18</address>

<address >10.1.1.18</address>

<address >127.0.0.1</address>

</ip>
<ip n="17" >
<address >10.1.1.18</address>

<address >10.1.1.18</address>

<address >127.0.0.1</address>

</ip>
<ip n="18" >
<address >10.1.1.19</address>

<address >10.1.1.19</address>

<address >127.0.0.1</address>

</ip>
<ip n="18" >
<address >10.1.1.19</address>

<address >10.1.1.19</address>

<address >127.0.0.1</address>

</ip>
<ip n="18" >
<address >10.1.1.19</address>

<address >10.1.1.19</address>

<address >127.0.0.1</address>

</ip>
<ip n="19" >
<address >10.1.1.20</address>

<address >10.1.1.20</address>

<address >127.0.0.1</address>

</ip>
<ip n="19" >
<address >10.1.1.20</address>

<address >10.1.1.20</address>

<address >127.0.0.1</address>

</ip>
<ip n="19" >
<address >10.1.1.20</address>

<address >10.1.1.20</address>

<address >127.0.0.1</address>

</ip>
<ip n="20" >
<address >10.1.1.21</address>

<address >10.1.1.21</address>

<address >127.0.0.1</address>

</ip>
<ip n="20" >
<address >10.1.1.21</address>

<address >10.1.1.21</address>

<address >127.0.0.1</address>

</ip>
<ip n="20" >
<address >10.1.1.21</address>

<address >10.1.1.21</address>

<address >127.0.0.1</address>

</ip>
<ip n="21" >
<address >10.1.1.22</address>

<address >10.1.1.22</address>

<address >127.0.0.1</address>

</ip>
<ip n="21" >
<address >10.1.1.22</address>

<address >10.1.1.22</address>

<address >127.0.0.1</address>

</ip>
<ip n="21" >
<address >10.1.1.22</address>

<address >10.1.1.22</address>

<address >127.0.0.1</address>

</ip>
<ip n="22" >
<address >10.1.1.23</address>

<address >10.1.1.23</address>

<address >127.0.0.1</address>

</ip>
<ip n="22" >
<address >10.1.1.23</address>

<address >10.1.1.23</address>

<address >127.0.0.1</address>

</ip>
<ip n="22" >
<address >10.1.1.23</address>

<address >10.1.1.23</address>

<address >127.0.0.1</address>

</ip>
<ip n="23" >
<address >10.1.1.24</address>

<address >10.1.1.24</address>

<address >127.0.0.1</address>

</ip>
<ip n="23" >
<address >10.1.1.24</address>

<address >10.1.1.24</address>

<address >127.0.0.1</address>

</ip>
<ip n="23" >
<address >10.1.1.24</address>

<address >10.1.1.24</address>

<address >127.0.0.1</address>

</ip>
<ip n="24" >
<address >127.0.0.1</address>

<address >10.0.0.5</address>

<address >11.0.0.5</address>

</ip>
<ip n="24" >
<address >127.0.0.1</address>

<address >10.0.0.5</address>

<address >11.0.0.5</address>

</ip>
<ip n="24" >
<address >127.0.0.1</address>

<address >10.0.0.5</address>

<address >11.0.0.5</address>

</ip>
<ip n="25" >
<address >127.0.0.1</address>

<address >10.0.0.9</address>

<address >11.0.0.9</address>

</ip>
<ip n="25" >
<address >127.0.0.1</address>

<address >10.0.0.9</address>

<address >11.0.0.9</address>

</ip>
<ip n="25" >
<address >127.0.0.1</address>

<address >10.0.0.9</address>

<address >11.0.0.9</address>

</ip>
<ip n="26" >
<address >10.0.0.6</address>

<address >10.0.0.10</address>

<address >127.0.0.1</address>

<address >7.0.0.1</address>

<address >1.0.0.1</address>

</ip>
<ip n="26" >
<address >10.0.0.6</address>

<address >10.0.0.10</address>

<address >127.0.0.1</address>

<address >7.0.0.1</address>

<address >1.0.0.1</address>

</ip>
<ip n="26" >
<address >10.0.0.6</address>

<address >10.0.0.10</address>

<address >127.0.0.1</address>

<address >7.0.0.1</address>

<address >1.0.0.1</address>

</ip>
<ip n="26" >
<address >10.0.0.6</address>

<address >10.0.0.10</address>

<address >127.0.0.1</address>

<address >7.0.0.1</address>

<address >1.0.0.1</address>

</ip>
<ip n="26" >
<address >10.0.0.6</address>

<address >10.0.0.10</address>

<address >127.0.0.1</address>

<address >7.0.0.1</address>

<address >1.0.0.1</address>

</ip>
<ip n="27" >
<address >11.0.0.6</address>

<address >11.0.0.10</address>

<address >127.0.0.1</address>

</ip>
<ip n="27" >
<address >11.0.0.6</address>

<address >11.0.0.10</address>

<address >127.0.0.1</address>

</ip>
<ip n="27" >
<address >11.0.0.6</address>

<address >11.0.0.10</address>

<address >127.0.0.1</address>

</ip>
<ip n="28" >
<address >1.0.0.2</address>

<address >127.0.0.1</address>

</ip>
<ip n="28" >
<address >1.0.0.2</address>

<address >127.0.0.1</address>

</ip>
<ipv6 n="0" >
<address >::1</address>

</ipv6>
<ipv6 n="1" >
<address >::1</address>

</ipv6>
<ipv6 n="2" >
<address >::1</address>

</ipv6>
<ipv6 n="3" >
<address >::1</address>

</ipv6>
<ipv6 n="4" >
<address >::1</address>

</ipv6>
<ipv6 n="5" >
<address >::1</address>

</ipv6>
<ipv6 n="6" >
<address >::1</address>

</ipv6>
<ipv6 n="7" >
<address >::1</address>

</ipv6>
<ipv6 n="8" >
<address >::1</address>

</ipv6>
<ipv6 n="9" >
<address >::1</address>

</ipv6>
<ipv6 n="10" >
<address >::1</address>

</ipv6>
<ipv6 n="11" >
<address >::1</address>

</ipv6>
<ipv6 n="12" >
<address >::1</address>

</ipv6>
<ipv6 n="13" >
<address >::1</address>

</ipv6>
<ipv6 n="14" >
<address >::1</address>

</ipv6>
<ipv6 n="15" >
<address >::1</address>

</ipv6>
<ipv6 n="16" >
<address >::1</address>

</ipv6>
<ipv6 n="17" >
<address >::1</address>

</ipv6>
<ipv6 n="18" >
<address >::1</address>

</ipv6>
<ipv6 n="19" >
<address >::1</address>

</ipv6>
<ipv6 n="20" >
<address >::1</address>

</ipv6>
<ipv6 n="21" >
<address >::1</address>

</ipv6>
<ipv6 n="22" >
<address >::1</address>

</ipv6>
<ipv6 n="23" >
<address >::1</address>

</ipv6>
<ipv6 n="24" >
<address >::1</address>

</ipv6>
<ipv6 n="25" >
<address >::1</address>

</ipv6>
<ipv6 n="26" >
<address >::1</address>

<address >fe80::200:ff:fe00:1</address>

<address >7777:f00d::200:ff:fe00:1</address>

</ipv6>
<ipv6 n="27" >
<address >::1</address>

</ipv6>
<ipv6 n="28" >
<address >::1</address>

</ipv6>
<nu p="s" t="0" id="0" w="1" h="1" />
<nu p="s" t="0" id="1" w="1" h="1" />
<nu p="s" t="0" id="2" w="1" h="1" />
<nu p="s" t="0" id="3" w="1" h="1" />
<nu p="s" t="0" id="4" w="1" h="1" />
<nu p="s" t="0" id="5" w="1" h="1" />
<nu p="s" t="0" id="6" w="1" h="1" />
<nu p="s" t="0" id="7" w="1" h="1" />
<nu p="s" t="0" id="8" w="1" h="1" />
<nu p="s" t="0" id="9" w="1" h="1" />
<nu p="s" t="0" id="10" w="1" h="1" />
<nu p="s" t="0" id="11" w="1" h="1" />
<nu p="s" t="0" id="12" w="1" h="1" />
<nu p="s" t="0" id="13" w="1" h="1" />
<nu p="s" t="0" id="14" w="1" h="1" />
<nu p="s" t="0" id="15" w="1" h="1" />
<nu p="s" t="0" id="16" w="1" h="1" />
<nu p="s" t="0" id="17" w="1" h="1" />
<nu p="s" t="0" id="18" w="1" h="1" />
<nu p="s" t="0" id="19" w="1" h="1" />
<nu p="s" t="0" id="20" w="1" h="1" />
<nu p="s" t="0" id="21" w="1" h="1" />
<nu p="s" t="0" id="22" w="1" h="1" />
<nu p="s" t="0" id="23" w="1" h="1" />
<nu p="s" t="0" id="24" w="1" h="1" />
<nu p="s" t="0" id="25" w="1" h="1" />
<nu p="s" t="0" id="26" w="1" h="1" />
<nu p="s" t="0" id="27" w="1" h="1" />
<nu p="s" t="0" id="28" w="1" h="1" />
<ncs ncId="0" n="RemainingEnergy" t="DOUBLE" />
<nu p="d" t="0" id="24" descr="GNB" />
<nu p="c" t="0" id="24" r="255" g="255" b="0" />
<nu p="d" t="0" id="25" descr="LTE" />
<nu p="c" t="0" id="25" r="255" g="255" b="0" />
<nu p="d" t="0" id="0" descr="UE" />
<nu p="c" t="0" id="0" r="0" g="255" b="0" />
<nu p="s" t="0" id="0" w="3" h="3" />
<nu p="d" t="0" id="1" descr="UE" />
<nu p="c" t="0" id="1" r="0" g="255" b="0" />
<nu p="s" t="0" id="1" w="3" h="3" />
<nu p="d" t="0" id="2" descr="UE" />
<nu p="c" t="0" id="2" r="0" g="255" b="0" />
<nu p="s" t="0" id="2" w="3" h="3" />
<nu p="d" t="0" id="3" descr="UE" />
<nu p="c" t="0" id="3" r="0" g="255" b="0" />
<nu p="s" t="0" id="3" w="3" h="3" />
<nu p="d" t="0" id="4" descr="UE" />
<nu p="c" t="0" id="4" r="0" g="255" b="0" />
<nu p="s" t="0" id="4" w="3" h="3" />
<nu p="d" t="0" id="5" descr="UE" />
<nu p="c" t="0" id="5" r="0" g="255" b="0" />
<nu p="s" t="0" id="5" w="3" h="3" />
<nu p="d" t="0" id="6" descr="UE" />
<nu p="c" t="0" id="6" r="0" g="255" b="0" />
<nu p="s" t="0" id="6" w="3" h="3" />
<nu p="d" t="0" id="7" descr="UE" />
<nu p="c" t="0" id="7" r="0" g="255" b="0" />
<nu p="s" t="0" id="7" w="3" h="3" />
<nu p="d" t="0" id="28" descr="RH" />
<nu p="c" t="0" id="28" r="0" g="0" b="255" />
<nu p="d" t="0" id="26" descr="PGW" />
<nu p="c" t="0" id="26" r="0" g="255" b="255" />
<nu p="d" t="0" id="27" descr="MME" />
<nu p="c" t="0" id="27" r="200" g="255" b="255" />
<nu p="p" t="0" id="8" x="86.16274451" y="58.97088335" />
<nu p="p" t="0" id="9" x="104.4571933" y="47.03087658" />
<nu p="p" t="0" id="10" x="77.67566506" y="55.04473523" />
<nu p="p" t="0" id="11" x="86.73111955" y="52.42192698" />
<nu p="p" t="0" id="12" x="79.77460094" y="72.81013787" />
<nu p="p" t="0" id="13" x="80.8496915" y="43.0967815" />
<nu p="p" t="0" id="14" x="87.36614674" y="60.66027176" />
<nu p="p" t="0" id="15" x="84.96217832" y="57.75849453" />
<nu p="p" t="0" id="16" x="53.13499313" y="48.62582718" />
<nu p="p" t="0" id="17" x="56.93367873" y="77.88399856" />
<nu p="p" t="0" id="18" x="37.49010777" y="59.13914065" />
<nu p="p" t="0" id="19" x="53.65221246" y="66.93816278" />
<nu p="p" t="0" id="20" x="51.71950645" y="62.66547513" />
<nu p="p" t="0" id="21" x="62.89610537" y="51.47130704" />
<nu p="p" t="0" id="22" x="47.13124954" y="63.66798697" />
<nu p="p" t="0" id="23" x="54.85262147" y="81.85765016" />
<p fId="24" fbTx="0.003767856" lbTx="0.003767913" tId="27" fbRx="0.018767856" lbRx="0.018767913" />
<p fId="25" fbTx="0.003767856" lbTx="0.003767913" tId="27" fbRx="0.018767856" lbRx="0.018767913" />
<p fId="24" fbTx="0.003767913" lbTx="0.00376797" tId="27" fbRx="0.018767913" lbRx="0.01876797" />
<p fId="25" fbTx="0.003767913" lbTx="0.00376797" tId="27" fbRx="0.018767913" lbRx="0.01876797" />
<p fId="24" fbTx="0.00376797" lbTx="0.003768027" tId="27" fbRx="0.01876797" lbRx="0.018768027" />
<p fId="25" fbTx="0.00376797" lbTx="0.003768027" tId="27" fbRx="0.01876797" lbRx="0.018768027" />
<p fId="24" fbTx="0.003768027" lbTx="0.003768084" tId="27" fbRx="0.018768027" lbRx="0.018768084" />
<p fId="25" fbTx="0.003768027" lbTx="0.003768084" tId="27" fbRx="0.018768027" lbRx="0.018768084" />
<p fId="24" fbTx="0.003768084" lbTx="0.003768141" tId="27" fbRx="0.018768084" lbRx="0.018768141" />
<p fId="25" fbTx="0.003768084" lbTx="0.003768141" tId="27" fbRx="0.018768084" lbRx="0.018768141" />
<p fId="24" fbTx="0.003768141" lbTx="0.003768198" tId="27" fbRx="0.018768141" lbRx="0.018768198" />
<p fId="25" fbTx="0.003768141" lbTx="0.003768198" tId="27" fbRx="0.018768141" lbRx="0.018768198" />
<p fId="24" fbTx="0.003768198" lbTx="0.003768255" tId="27" fbRx="0.018768198" lbRx="0.018768255" />
<p fId="25" fbTx="0.003768198" lbTx="0.003768255" tId="27" fbRx="0.018768198" lbRx="0.018768255" />
<p fId="24" fbTx="0.003768255" lbTx="0.003768312" tId="27" fbRx="0.018768255" lbRx="0.018768312" />
<p fId="25" fbTx="0.003768255" lbTx="0.003768312" tId="27" fbRx="0.018768255" lbRx="0.018768312" />
<p fId="24" fbTx="0.003768312" lbTx="0.003768369" tId="27" fbRx="0.018768312" lbRx="0.018768369" />
<p fId="24" fbTx="0.003768369" lbTx="0.003768426" tId="27" fbRx="0.018768369" lbRx="0.018768426" />
<p fId="24" fbTx="0.003768426" lbTx="0.003768483" tId="27" fbRx="0.018768426" lbRx="0.018768483" />
<p fId="24" fbTx="0.003768483" lbTx="0.00376854" tId="27" fbRx="0.018768483" lbRx="0.01876854" />
<p fId="24" fbTx="0.00376854" lbTx="0.003768597" tId="27" fbRx="0.01876854" lbRx="0.018768597" />
<p fId="24" fbTx="0.003768597" lbTx="0.003768654" tId="27" fbRx="0.018768597" lbRx="0.018768654" />
<p fId="24" fbTx="0.003768654" lbTx="0.003768711" tId="27" fbRx="0.018768654" lbRx="0.018768711" />
<p fId="24" fbTx="0.003768711" lbTx="0.003768768" tId="27" fbRx="0.018768711" lbRx="0.018768768" />
<p fId="27" fbTx="0.018767913" lbTx="0.018768" tId="24" fbRx="0.033767913" lbRx="0.033768" />
<p fId="27" fbTx="0.018767913" lbTx="0.018768" tId="25" fbRx="0.033767913" lbRx="0.033768" />
<p fId="27" fbTx="0.018768" lbTx="0.018768087" tId="24" fbRx="0.033768" lbRx="0.033768087" />
<p fId="27" fbTx="0.018768" lbTx="0.018768087" tId="25" fbRx="0.033768" lbRx="0.033768087" />
<p fId="27" fbTx="0.018768087" lbTx="0.018768174" tId="24" fbRx="0.033768087" lbRx="0.033768174" />
<p fId="27" fbTx="0.018768087" lbTx="0.018768174" tId="25" fbRx="0.033768087" lbRx="0.033768174" />
<p fId="27" fbTx="0.018768174" lbTx="0.018768261" tId="24" fbRx="0.033768174" lbRx="0.033768261" />
<p fId="27" fbTx="0.018768174" lbTx="0.018768261" tId="25" fbRx="0.033768174" lbRx="0.033768261" />
<p fId="27" fbTx="0.018768261" lbTx="0.018768348" tId="24" fbRx="0.033768261" lbRx="0.033768348" />
<p fId="27" fbTx="0.018768261" lbTx="0.018768348" tId="25" fbRx="0.033768261" lbRx="0.033768348" />
<p fId="27" fbTx="0.018768348" lbTx="0.018768435" tId="24" fbRx="0.033768348" lbRx="0.033768435" />
<p fId="27" fbTx="0.018768348" lbTx="0.018768435" tId="25" fbRx="0.033768348" lbRx="0.033768435" />
<p fId="27" fbTx="0.018768435" lbTx="0.018768522" tId="24" fbRx="0.033768435" lbRx="0.033768522" />
<p fId="27" fbTx="0.018768435" lbTx="0.018768522" tId="25" fbRx="0.033768435" lbRx="0.033768522" />
<p fId="27" fbTx="0.018768522" lbTx="0.018768609" tId="24" fbRx="0.033768522" lbRx="0.033768609" />
<p fId="27" fbTx="0.018768522" lbTx="0.018768609" tId="25" fbRx="0.033768522" lbRx="0.033768609" />
<p fId="27" fbTx="0.018768609" lbTx="0.018768696" tId="24" fbRx="0.033768609" lbRx="0.033768696" />
<p fId="27" fbTx="0.018768696" lbTx="0.018768783" tId="24" fbRx="0.033768696" lbRx="0.033768783" />
<p fId="27" fbTx="0.018768783" lbTx="0.01876887" tId="24" fbRx="0.033768783" lbRx="0.03376887" />
<p fId="27" fbTx="0.01876887" lbTx="0.018768957" tId="24" fbRx="0.03376887" lbRx="0.033768957" />
<p fId="27" fbTx="0.018768957" lbTx="0.018769044" tId="24" fbRx="0.033768957" lbRx="0.033769044" />
<p fId="27" fbTx="0.018769044" lbTx="0.018769131" tId="24" fbRx="0.033769044" lbRx="0.033769131" />
<p fId="27" fbTx="0.018769131" lbTx="0.018769218" tId="24" fbRx="0.033769131" lbRx="0.033769218" />
<p fId="27" fbTx="0.018769218" lbTx="0.018769305" tId="24" fbRx="0.033769218" lbRx="0.033769305" />
<nu p="p" t="0.25" id="4" x="50.5" y="50" />
<nu p="p" t="0.25" id="8" x="85.79229198" y="59.85144005" />
<nu p="p" t="0.25" id="9" x="104.503869" y="46.25639343" />
<nu p="p" t="0.25" id="10" x="76.98409234" y="55.04925272" />
<nu p="p" t="0.25" id="11" x="85.82261485" y="52.47422212" />
<nu p="p" t="0.25" id="12" x="79.50892544" y="73.29731463" />
<nu p="p" t="0.25" id="13" x="80.46463088" y="42.43607822" />
<nu p="p" t="0.25" id="14" x="86.87354995" y="60.06756719" />
<nu p="p" t="0.25" id="15" x="85.85364497" y="57.47490579" />
<nu p="p" t="0.25" id="16" x="55.80887391" y="50.26642726" />
<nu p="p" t="0.25" id="17" x="60.07551284" y="78.50084932" />
<nu p="p" t="0.25" id="18" x="36.90032213" y="60.32997971" />
<nu p="p" t="0.25" id="19" x="54.747324" y="68.99432705" />
<nu p="p" t="0.25" id="21" x="61.61721044" y="49.58237196" />
<nu p="p" t="0.25" id="22" x="43.70093481" y="63.35169927" />
<nu p="p" t="0.25" id="23" x="54.40852872" y="80.53794701" />
<nu p="p" t="0.5" id="4" x="53" y="50" />
<nu p="p" t="0.5" id="8" x="85.42183945" y="60.73199675" />
<nu p="p" t="0.5" id="9" x="104.5505448" y="45.48191028" />
<nu p="p" t="0.5" id="11" x="84.91411015" y="52.52651725" />
<nu p="p" t="0.5" id="13" x="80.07957025" y="41.77537494" />
<nu p="p" t="0.5" id="14" x="86.38095315" y="59.47486261" />
<nu p="p" t="0.5" id="15" x="86.74511162" y="57.19131705" />
<nu p="p" t="0.5" id="16" x="58.48275469" y="51.90702734" />
<nu p="p" t="0.5" id="17" x="63.21734694" y="79.11770008" />
<nu p="p" t="0.5" id="18" x="36.31053648" y="61.52081877" />
<nu p="p" t="0.5" id="19" x="55.84243553" y="71.05049131" />
<nu p="p" t="0.5" id="20" x="51.00368337" y="61.87262216" />
<nu p="p" t="0.5" id="21" x="60.33831551" y="47.69343689" />
<nu p="p" t="0.5" id="22" x="40.27062007" y="63.03541158" />
<nu p="p" t="0.5" id="23" x="53.96443597" y="79.21824387" />
<nu p="p" t="0.551660212" id="13" x="80.000001" y="41.63884665" />
<nu p="p" t="0.75" id="4" x="55.5" y="50" />
<nu p="p" t="0.75" id="8" x="85.05138692" y="61.61255345" />
<nu p="p" t="0.75" id="9" x="104.5972205" y="44.70742713" />
<nu p="p" t="0.75" id="10" x="75.60094692" y="55.05828768" />
<nu p="p" t="0.75" id="12" x="78.97757446" y="74.27166813" />
<nu p="p" t="0.75" id="13" x="79.89938364" y="42.09342217" />
<nu p="p" t="0.75" id="14" x="85.88835636" y="58.88215804" />
<nu p="p" t="0.75" id="15" x="87.63657828" y="56.90772831" />
<nu p="p" t="0.75" id="16" x="61.15663547" y="53.54762742" />
<nu p="p" t="0.75" id="17" x="66.35918104" y="79.73455084" />
<nu p="p" t="0.75" id="18" x="35.72075084" y="62.71165783" />
<nu p="p" t="0.75" id="19" x="56.93754706" y="73.10665557" />
<nu p="p" t="0.75" id="20" x="50.64577183" y="61.47619567" />
<nu p="p" t="0.75" id="21" x="59.05942057" y="45.80450181" />
<nu p="p" t="0.75" id="22" x="36.84030534" y="62.71912388" />
<nu p="p" t="0.75" id="23" x="53.52034321" y="77.89854072" />
<nu p="p" t="0.856475577" id="21" x="58.51473627" y="45" />
<nu p="p" t="0.884120735" id="22" x="35.00000001" y="62.54944093" />
<nu p="p" t="1" id="4" x="58" y="50" />
<nu p="p" t="1" id="8" x="84.68093439" y="62.49311015" />
<nu p="p" t="1" id="9" x="104.6438962" y="43.93294399" />
<nu p="p" t="1" id="10" x="74.9093742" y="55.06280516" />
<nu p="p" t="1" id="11" x="83.09710074" y="52.63110752" />
<nu p="p" t="1" id="15" x="88.52804493" y="56.62413957" />
<nu p="p" t="1" id="16" x="63.83051625" y="55.18822749" />
<nu p="p" t="1" id="17" x="69.50101514" y="80.3514016" />
<nu p="p" t="1" id="18" x="35.13096519" y="63.90249689" />
<nu p="p" t="1" id="19" x="58.0326586" y="75.16281984" />
<nu p="p" t="1" id="21" x="57.78052564" y="46.08443327" />
<nu p="p" t="1" id="22" x="36.59000941" y="62.40283619" />
<nu p="p" t="1" id="23" x="53.07625046" y="76.57883758" />
<nu p="p" t="1.055513893" id="18" x="35" y="64.16692934" />
<nu p="p" t="1.25" id="4" x="60.5" y="50" />
<nu p="p" t="1.25" id="8" x="84.31048186" y="63.37366685" />
<nu p="p" t="1.25" id="11" x="82.18859604" y="52.68340266" />
<nu p="p" t="1.25" id="12" x="78.44622347" y="75.24602163" />
<nu p="p" t="1.25" id="13" x="79.64573469" y="43.23937356" />
<nu p="p" t="1.25" id="14" x="84.90316278" y="57.69674889" />
<nu p="p" t="1.25" id="15" x="89.41951159" y="56.34055083" />
<nu p="p" t="1.25" id="16" x="66.50439703" y="56.82882757" />
<nu p="p" t="1.25" id="17" x="72.64284924" y="80.96825236" />
<nu p="p" t="1.25" id="18" x="35.45882046" y="65.09333595" />
<nu p="p" t="1.25" id="19" x="59.12777013" y="77.2189841" />
<nu p="p" t="1.25" id="20" x="49.92994876" y="60.6833427" />
<nu p="p" t="1.25" id="21" x="56.50163071" y="47.97336835" />
<nu p="p" t="1.25" id="22" x="40.02032414" y="62.08654849" />
<nu p="p" t="1.25" id="23" x="52.63215771" y="75.25913444" />
<nu p="p" t="1.437561682" id="17" x="75" y="81.43104263" />
<nu p="p" t="1.5" id="4" x="63" y="50" />
<nu p="p" t="1.5" id="8" x="83.94002933" y="64.25422355" />
<nu p="p" t="1.5" id="9" x="104.7372477" y="42.38397769" />
<nu p="p" t="1.5" id="10" x="73.52622877" y="55.07184012" />
<nu p="p" t="1.5" id="11" x="81.28009134" y="52.73569779" />
<nu p="p" t="1.5" id="15" x="90.31097824" y="56.05696209" />
<nu p="p" t="1.5" id="16" x="69.17827781" y="58.46942765" />
<nu p="p" t="1.5" id="18" x="36.0486061" y="66.28417501" />
<nu p="p" t="1.5" id="19" x="60.22288167" y="79.27514837" />
<nu p="p" t="1.5" id="21" x="55.22273578" y="49.86230342" />
<nu p="p" t="1.5" id="22" x="43.45063887" y="61.77026079" />
<nu p="p" t="1.5" id="23" x="52.18806496" y="73.93943129" />
<nu p="p" t="1.75" id="4" x="65.5" y="50" />
<nu p="p" t="1.75" id="8" x="83.5695768" y="65.13478025" />
<nu p="p" t="1.75" id="9" x="104.7839234" y="41.60949454" />
<nu p="p" t="1.75" id="10" x="72.83465606" y="55.0763576" />
<nu p="p" t="1.75" id="11" x="80.37158664" y="52.78799293" />
<nu p="p" t="1.75" id="12" x="77.91487249" y="76.22037514" />
<nu p="p" t="1.75" id="13" x="79.39208574" y="44.38532496" />
<nu p="p" t="1.75" id="14" x="83.9179692" y="56.51133975" />
<nu p="p" t="1.75" id="15" x="91.20244489" y="55.77337335" />
<nu p="p" t="1.75" id="16" x="71.85215859" y="60.11002773" />
<nu p="p" t="1.75" id="17" x="71.07348255" y="82.20195389" />
<nu p="p" t="1.75" id="18" x="36.63839175" y="67.47501407" />
<nu p="p" t="1.75" id="19" x="61.3179932" y="81.33131263" />
<nu p="p" t="1.75" id="20" x="49.21412568" y="59.89048973" />
<nu p="p" t="1.75" id="21" x="53.94384085" y="51.7512385" />
<nu p="p" t="1.75" id="22" x="46.88095361" y="61.4539731" />
<nu p="p" t="1.75" id="23" x="51.7439722" y="72.61972815" />
<nu p="p" t="2" id="4" x="68" y="50" />
<nu p="p" t="2" id="8" x="83.19912427" y="66.01533695" />
<nu p="p" t="2" id="9" x="104.8305991" y="40.83501139" />
<nu p="p" t="2" id="11" x="79.46308194" y="52.84028806" />
<nu p="p" t="2" id="14" x="83.42537241" y="55.91863517" />
<nu p="p" t="2" id="15" x="92.09391155" y="55.48978461" />
<nu p="p" t="2" id="16" x="74.52603936" y="61.75062781" />
<nu p="p" t="2" id="17" x="67.93164845" y="82.81880465" />
<nu p="p" t="2" id="18" x="37.22817739" y="68.66585313" />
<nu p="p" t="2" id="19" x="62.41310474" y="83.38747689" />
<nu p="p" t="2" id="20" x="48.85621414" y="59.49406324" />
<nu p="p" t="2" id="21" x="52.66494592" y="53.64017358" />
<nu p="p" t="2" id="22" x="50.31126834" y="61.1376854" />
<nu p="p" t="2" id="23" x="51.29987945" y="71.30002501" />
<nu p="p" t="2.044313927" id="16" x="75" y="62.04143354" />
<nu p="p" t="2.177153328" id="22" x="52.74203503" y="60.91355973" />
<nu p="p" t="2.196059616" id="19" x="63.27193333" y="85" />
<nu p="p" t="2.25" id="4" x="70.5" y="50" />
<nu p="p" t="2.25" id="8" x="82.82867174" y="66.89589365" />
<nu p="p" t="2.25" id="10" x="71.45151063" y="55.08539256" />
<nu p="p" t="2.25" id="11" x="78.55457724" y="52.8925832" />
<nu p="p" t="2.25" id="12" x="77.3835215" y="77.19472864" />
<nu p="p" t="2.25" id="13" x="79.13843679" y="45.53127636" />
<nu p="p" t="2.25" id="14" x="82.93277562" y="55.3259306" />
<nu p="p" t="2.25" id="16" x="72.80007985" y="63.39122789" />
<nu p="p" t="2.25" id="17" x="64.78981435" y="83.43565541" />
<nu p="p" t="2.25" id="18" x="37.81796304" y="69.85669219" />
<nu p="p" t="2.25" id="21" x="51.38605099" y="55.52910866" />
<nu p="p" t="2.25" id="22" x="51.91093608" y="60.92537133" />
<nu p="p" t="2.25" id="23" x="50.8557867" y="69.98032186" />
<nu p="p" t="2.269538269" id="9" x="104.8809227" y="40" />
<nu p="p" t="2.342420598" id="17" x="63.6283336" y="83.66369428" />
<nu p="p" t="2.390766045" id="16" x="71.29451336" y="64.31499103" />
<nu p="p" t="2.5" id="4" x="73" y="50" />
<nu p="p" t="2.5" id="8" x="82.4582192" y="67.77645035" />
<nu p="p" t="2.5" id="10" x="70.75993792" y="55.08991004" />
<nu p="p" t="2.5" id="11" x="77.64607254" y="52.94487833" />
<nu p="p" t="2.5" id="13" x="79.01161232" y="46.10425206" />
<nu p="p" t="2.5" id="14" x="82.44017882" y="54.73322603" />
<nu p="p" t="2.5" id="15" x="93.87684485" y="54.92260712" />
<nu p="p" t="2.5" id="16" x="71.02586325" y="63.0069941" />
<nu p="p" t="2.5" id="17" x="64.6028069" y="84.23928538" />
<nu p="p" t="2.5" id="18" x="38.40774868" y="71.04753125" />
<nu p="p" t="2.5" id="19" x="64.60332781" y="82.50019458" />
<nu p="p" t="2.5" id="20" x="48.14039107" y="58.70121027" />
<nu p="p" t="2.5" id="21" x="50.10715606" y="57.41804373" />
<nu p="p" t="2.5" id="22" x="49.05871606" y="60.96590717" />
<nu p="p" t="2.5" id="23" x="50.41169394" y="68.66061872" />
<nu p="p" t="2.708260612" id="17" x="65.89069353" y="85" />
<nu p="p" t="2.75" id="4" x="75.5" y="50" />
<nu p="p" t="2.75" id="8" x="82.08776667" y="68.65700705" />
<nu p="p" t="2.75" id="9" x="104.9706263" y="41.48843806" />
<nu p="p" t="2.75" id="11" x="76.73756784" y="52.99717347" />
<nu p="p" t="2.75" id="12" x="76.85217052" y="78.16908215" />
<nu p="p" t="2.75" id="13" x="78.88478784" y="46.67722775" />
<nu p="p" t="2.75" id="14" x="81.94758203" y="54.14052145" />
<nu p="p" t="2.75" id="15" x="94.76831151" y="54.63901838" />
<nu p="p" t="2.75" id="16" x="70.41101298" y="60.01342648" />
<nu p="p" t="2.75" id="17" x="66.14881051" y="84.84753832" />
<nu p="p" t="2.75" id="18" x="38.99753433" y="72.23837031" />
<nu p="p" t="2.75" id="19" x="65.69843934" y="80.44403031" />
<nu p="p" t="2.75" id="20" x="47.78247953" y="58.30478379" />
<nu p="p" t="2.75" id="21" x="48.82826112" y="59.30697881" />
<nu p="p" t="2.75" id="22" x="46.20649603" y="61.00644301" />
<nu p="p" t="2.75" id="23" x="49.96760119" y="67.34091557" />
<nu p="p" t="2.774713672" id="10" x="70" y="55.0948741" />
<nu p="p" t="3" id="4" x="78" y="50" />
<nu p="p" t="3" id="8" x="81.71731414" y="69.53756375" />
<nu p="p" t="3" id="9" x="105.0173021" y="42.26292121" />
<nu p="p" t="3" id="10" x="70.62320751" y="55.098945" />
<nu p="p" t="3" id="11" x="75.82906313" y="53.0494686" />
<nu p="p" t="3" id="13" x="78.75796337" y="47.25020345" />
<nu p="p" t="3" id="14" x="81.45498524" y="53.54781688" />
<nu p="p" t="3" id="15" x="95.65977816" y="54.35542964" />
<nu p="p" t="3" id="16" x="69.7961627" y="57.01985886" />
<nu p="p" t="3" id="17" x="67.69481412" y="83.93436202" />
<nu p="p" t="3" id="18" x="39.58731997" y="73.42920937" />
<nu p="p" t="3" id="19" x="66.79355088" y="78.38786605" />
<nu p="p" t="3" id="20" x="47.42456799" y="57.9083573" />
<nu p="p" t="3" id="21" x="47.54936619" y="61.19591389" />
<nu p="p" t="3" id="22" x="43.35427601" y="61.04697885" />
<nu p="p" t="3" id="23" x="49.52350844" y="66.02121243" />
<nu p="p" t="3.219423586" id="19" x="67.75472408" y="76.5831823" />
<nu p="p" t="3.25" id="4" x="80.5" y="50" />
<nu p="p" t="3.25" id="8" x="81.34686161" y="70.41812045" />
<nu p="p" t="3.25" id="9" x="105.0639778" y="43.03740436" />
<nu p="p" t="3.25" id="10" x="71.31478022" y="55.10346248" />
<nu p="p" t="3.25" id="11" x="74.92055843" y="53.10176374" />
<nu p="p" t="3.25" id="12" x="76.32081953" y="79.14343565" />
<nu p="p" t="3.25" id="14" x="80.96238845" y="52.95511231" />
<nu p="p" t="3.25" id="15" x="96.55124481" y="54.0718409" />
<nu p="p" t="3.25" id="16" x="69.18131243" y="54.02629124" />
<nu p="p" t="3.25" id="17" x="69.24081773" y="83.02118572" />
<nu p="p" t="3.25" id="18" x="40.17710562" y="74.62004843" />
<nu p="p" t="3.25" id="21" x="46.27047126" y="63.08484896" />
<nu p="p" t="3.25" id="22" x="40.50205598" y="61.08751469" />
<nu p="p" t="3.25" id="23" x="49.07941568" y="64.70150929" />
<nu p="p" t="3.28781452" id="21" x="46.07702807" y="63.37056566" />
<nu p="p" t="3.5" id="4" x="83" y="50" />
<nu p="p" t="3.5" id="8" x="80.97640908" y="71.29867715" />
<nu p="p" t="3.5" id="10" x="72.00635294" y="55.10797996" />
<nu p="p" t="3.5" id="13" x="78.50431442" y="48.39615485" />
<nu p="p" t="3.5" id="15" x="97.44271147" y="53.78825216" />
<nu p="p" t="3.5" id="16" x="68.56646215" y="51.03272362" />
<nu p="p" t="3.5" id="17" x="70.78682134" y="82.10800942" />
<nu p="p" t="3.5" id="18" x="40.76689126" y="75.81088749" />
<nu p="p" t="3.5" id="19" x="65.23701439" y="78.08667549" />
<nu p="p" t="3.5" id="20" x="46.70874492" y="57.11550433" />
<nu p="p" t="3.5" id="21" x="47.51230902" y="63.6796948" />
<nu p="p" t="3.5" id="22" x="37.64983596" y="61.12805054" />
<nu p="p" t="3.5" id="23" x="48.63532293" y="63.38180614" />
<nu p="p" t="3.689555225" id="12" x="75.85370333" y="80" />
<nu p="p" t="3.73226083" id="22" x="35" y="61.16571009" />
<nu p="p" t="3.738425558" id="14" x="80.000001" y="51.79714406" />
<nu p="p" t="3.75" id="4" x="85.5" y="50" />
<nu p="p" t="3.75" id="8" x="80.60595655" y="72.17923385" />
<nu p="p" t="3.75" id="9" x="105.1573292" y="44.58637065" />
<nu p="p" t="3.75" id="11" x="73.10354903" y="53.20635401" />
<nu p="p" t="3.75" id="15" x="98.33417812" y="53.50466342" />
<nu p="p" t="3.75" id="16" x="67.95161188" y="48.039156" />
<nu p="p" t="3.75" id="17" x="72.33282495" y="81.19483311" />
<nu p="p" t="3.75" id="18" x="41.35667691" y="77.00172655" />
<nu p="p" t="3.75" id="19" x="62.99367749" y="79.4263223" />
<nu p="p" t="3.75" id="20" x="46.35083338" y="56.71907784" />
<nu p="p" t="3.75" id="21" x="49.20337779" y="64.04391524" />
<nu p="p" t="3.75" id="22" x="35.20238406" y="61.16858638" />
<nu p="p" t="3.75" id="23" x="48.19123018" y="62.062103" />
<nu p="p" t="4" id="4" x="88" y="50" />
<nu p="p" t="4" id="8" x="80.23550402" y="73.05979055" />
<nu p="p" t="4" id="9" x="105.204005" y="45.3608538" />
<nu p="p" t="4" id="10" x="73.38949837" y="55.11701492" />
<nu p="p" t="4" id="11" x="72.19504433" y="53.25864914" />
<nu p="p" t="4" id="13" x="78.25066547" y="49.54210625" />
<nu p="p" t="4" id="14" x="80.20697082" y="52.5575418" />
<nu p="p" t="4" id="15" x="99.22564477" y="53.22107468" />
<nu p="p" t="4" id="16" x="67.3367616" y="45.04558838" />
<nu p="p" t="4" id="17" x="73.87882855" y="80.28165681" />
<nu p="p" t="4" id="18" x="41.94646255" y="78.19256561" />
<nu p="p" t="4" id="19" x="60.7503406" y="80.76596911" />
<nu p="p" t="4" id="20" x="45.99292184" y="56.32265136" />
<nu p="p" t="4" id="21" x="50.89444655" y="64.40813567" />
<nu p="p" t="4" id="22" x="38.05460409" y="61.20912222" />
<nu p="p" t="4" id="23" x="47.74713742" y="60.74239985" />
<nu p="p" t="4.003807195" id="16" x="67.32739818" y="45" />
<nu p="p" t="4.181301557" id="17" x="75" y="79.61941567" />
<nu p="p" t="4.25" id="4" x="90.5" y="50" />
<nu p="p" t="4.25" id="8" x="79.86505149" y="73.94034725" />
<nu p="p" t="4.25" id="9" x="105.2506807" y="46.13533695" />
<nu p="p" t="4.25" id="10" x="74.08107108" y="55.12153241" />
<nu p="p" t="4.25" id="11" x="71.28653963" y="53.31094428" />
<nu p="p" t="4.25" id="12" x="75.25811757" y="78.90785734" />
<nu p="p" t="4.25" id="13" x="78.12384099" y="50.11508195" />
<nu p="p" t="4.25" id="14" x="80.40478241" y="53.28429261" />
<nu p="p" t="4.25" id="15" x="100.1171114" y="52.93748594" />
<nu p="p" t="4.25" id="16" x="66.72191133" y="47.94797924" />
<nu p="p" t="4.25" id="18" x="42.5362482" y="79.38340467" />
<nu p="p" t="4.25" id="19" x="58.5070037" y="82.10561592" />
<nu p="p" t="4.25" id="20" x="45.6350103" y="55.92622487" />
<nu p="p" t="4.25" id="21" x="52.58551531" y="64.7723561" />
<nu p="p" t="4.25" id="22" x="40.90682411" y="61.24965806" />
<nu p="p" t="4.25" id="23" x="47.30304467" y="59.42269671" />
<nu p="p" t="4.5" id="4" x="93" y="50" />
<nu p="p" t="4.5" id="8" x="79.49459896" y="74.82090395" />
<nu p="p" t="4.5" id="11" x="70.37803493" y="53.36323941" />
<nu p="p" t="4.5" id="12" x="74.99244207" y="78.42068059" />
<nu p="p" t="4.5" id="13" x="77.99701652" y="50.68805765" />
<nu p="p" t="4.5" id="14" x="80.602594" y="54.01104341" />
<nu p="p" t="4.5" id="15" x="101.0085781" y="52.6538972" />
<nu p="p" t="4.5" id="16" x="66.10706106" y="50.94154686" />
<nu p="p" t="4.5" id="17" x="73.02916423" y="78.45530421" />
<nu p="p" t="4.5" id="18" x="43.12603384" y="80.57424372" />
<nu p="p" t="4.5" id="19" x="56.26366681" y="83.44526273" />
<nu p="p" t="4.5" id="21" x="54.27658408" y="65.13657653" />
<nu p="p" t="4.5" id="22" x="43.75904414" y="61.2901939" />
<nu p="p" t="4.5" id="23" x="46.85895192" y="58.10299357" />
<nu p="p" t="4.604026685" id="11" x="70" y="53.38499977" />
<nu p="p" t="4.75" id="4" x="95.5" y="50" />
<nu p="p" t="4.75" id="8" x="79.12414643" y="75.70146066" />
<nu p="p" t="4.75" id="9" x="105.3440322" y="47.68430325" />
<nu p="p" t="4.75" id="10" x="75.46421651" y="55.13056737" />
<nu p="p" t="4.75" id="11" x="70.53046977" y="53.41553455" />
<nu p="p" t="4.75" id="12" x="74.72676658" y="77.93350383" />
<nu p="p" t="4.75" id="13" x="77.87019204" y="51.26103334" />
<nu p="p" t="4.75" id="16" x="65.49221078" y="53.93511448" />
<nu p="p" t="4.75" id="17" x="71.48316062" y="77.54212791" />
<nu p="p" t="4.75" id="18" x="43.71581949" y="81.76508278" />
<nu p="p" t="4.75" id="19" x="54.02032991" y="84.78490953" />
<nu p="p" t="4.75" id="20" x="44.91918722" y="55.1333719" />
<nu p="p" t="4.75" id="21" x="55.96765284" y="65.50079696" />
<nu p="p" t="4.75" id="22" x="46.61126416" y="61.33072974" />
<nu p="p" t="4.75" id="23" x="46.41485917" y="56.78329042" />
<nu p="p" t="4.790139398" id="19" x="53.66014514" y="85" />
<nu p="p" t="4.806418468" id="22" x="47.2549357" y="61.33987762" />
<nu p="p" t="4.844908283" id="16" x="65.25879325" y="55.07157193" />
<nu p="p" t="5" id="4" x="98" y="50" />
<nu p="p" t="5" id="8" x="78.7536939" y="76.58201736" />
<nu p="p" t="5" id="9" x="105.3907079" y="48.4587864" />
<nu p="p" t="5" id="10" x="76.15578922" y="55.13508485" />
<nu p="p" t="5" id="11" x="71.43897447" y="53.46782968" />
<nu p="p" t="5" id="14" x="80.99821718" y="55.46454502" />
<nu p="p" t="5" id="15" x="102.7915114" y="52.08671971" />
<nu p="p" t="5" id="16" x="64.51901813" y="55.17427924" />
<nu p="p" t="5" id="17" x="69.93715701" y="76.62895161" />
<nu p="p" t="5" id="18" x="44.30560513" y="82.95592184" />
<nu p="p" t="5" id="19" x="51.77699302" y="83.87544366" />
<nu p="p" t="5" id="20" x="44.56127569" y="54.73694541" />
<nu p="p" t="5" id="21" x="57.65872161" y="65.86501739" />
<nu p="p" t="5" id="22" x="46.22536314" y="62.51917733" />
<nu p="p" t="5" id="23" x="45.97076641" y="55.46358728" />
<nu p="p" t="5.25" id="4" x="100.5" y="50" />
<nu p="p" t="5.25" id="8" x="78.38324137" y="77.46257406" />
<nu p="p" t="5.25" id="9" x="105.4373836" y="49.23326955" />
<nu p="p" t="5.25" id="11" x="72.34747917" y="53.52012482" />
<nu p="p" t="5.25" id="12" x="74.1954156" y="76.95915033" />
<nu p="p" t="5.25" id="13" x="77.61654309" y="52.40698474" />
<nu p="p" t="5.25" id="14" x="81.19602877" y="56.19129583" />
<nu p="p" t="5.25" id="15" x="103.682978" y="51.80313097" />
<nu p="p" t="5.25" id="16" x="63.32653807" y="55.33983822" />
<nu p="p" t="5.25" id="17" x="68.3911534" y="75.71577531" />
<nu p="p" t="5.25" id="18" x="44.89539078" y="84.1467609" />
<nu p="p" t="5.25" id="19" x="49.53365612" y="82.53579685" />
<nu p="p" t="5.25" id="21" x="59.34979037" y="66.22923782" />
<nu p="p" t="5.25" id="22" x="44.89572629" y="64.04217863" />
<nu p="p" t="5.25" id="23" x="45.52667366" y="54.14388414" />
<nu p="p" t="5.386304044" id="23" x="45.28454711" y="53.42436063" />
<nu p="p" t="5.429125611" id="18" x="45.31797364" y="85" />
<nu p="p" t="5.5" id="4" x="103" y="50" />
<nu p="p" t="5.5" id="8" x="78.01278884" y="78.34313076" />
<nu p="p" t="5.5" id="9" x="105.4840594" y="50.0077527" />
<nu p="p" t="5.5" id="10" x="77.53893465" y="55.14411981" />
<nu p="p" t="5.5" id="11" x="73.25598387" y="53.57241995" />
<nu p="p" t="5.5" id="12" x="73.9297401" y="76.47197358" />
<nu p="p" t="5.5" id="15" x="104.5744447" y="51.51954223" />
<nu p="p" t="5.5" id="16" x="62.13405801" y="55.5053972" />
<nu p="p" t="5.5" id="17" x="66.84514979" y="74.802599" />
<nu p="p" t="5.5" id="19" x="47.29031923" y="81.19615004" />
<nu p="p" t="5.5" id="20" x="43.84545261" y="53.94409244" />
<nu p="p" t="5.5" id="21" x="61.04085914" y="66.59345825" />
<nu p="p" t="5.5" id="22" x="43.56608944" y="65.56517994" />
<nu p="p" t="5.5" id="23" x="44.59790198" y="52.84547604" />
<nu p="p" t="5.643814157" id="18" x="45.82445453" y="83.97736197" />
<nu p="p" t="5.75" id="4" x="105.5" y="50" />
<nu p="p" t="5.75" id="8" x="77.64233631" y="79.22368746" />
<nu p="p" t="5.75" id="10" x="78.23050736" y="55.14863729" />
<nu p="p" t="5.75" id="11" x="74.16448858" y="53.62471509" />
<nu p="p" t="5.75" id="12" x="73.66406461" y="75.98479683" />
<nu p="p" t="5.75" id="13" x="77.36289414" y="53.55293614" />
<nu p="p" t="5.75" id="14" x="81.59165195" y="57.64479744" />
<nu p="p" t="5.75" id="15" x="105.4659113" y="51.23595349" />
<nu p="p" t="5.75" id="16" x="60.94157795" y="55.67095618" />
<nu p="p" t="5.75" id="17" x="65.29914618" y="73.8894227" />
<nu p="p" t="5.75" id="18" x="46.39399912" y="83.52593673" />
<nu p="p" t="5.75" id="19" x="45.04698233" y="79.85650323" />
<nu p="p" t="5.75" id="21" x="62.7319279" y="66.95767868" />
<nu p="p" t="5.75" id="22" x="42.23645259" y="67.08818125" />
<nu p="p" t="5.75" id="23" x="43.08807446" y="51.57259743" />
<nu p="p" t="5.970403905" id="8" x="77.31573957" y="80" />
<nu p="p" t="6" id="4" x="108" y="50" />
<nu p="p" t="6" id="9" x="105.5774108" y="51.556719" />
<nu p="p" t="6" id="11" x="75.07299328" y="53.67701022" />
<nu p="p" t="6" id="13" x="77.23606967" y="54.12591184" />
<nu p="p" t="6" id="14" x="81.78946354" y="58.37154824" />
<nu p="p" t="6" id="15" x="106.357378" y="50.95236475" />
<nu p="p" t="6" id="16" x="59.7490979" y="55.83651517" />
<nu p="p" t="6" id="17" x="63.75314257" y="72.9762464" />
<nu p="p" t="6" id="18" x="47.73491373" y="82.46311792" />
<nu p="p" t="6" id="19" x="42.80364544" y="78.51685642" />
<nu p="p" t="6" id="21" x="64.42299667" y="67.32189911" />
<nu p="p" t="6" id="22" x="40.90681573" y="68.61118256" />
<nu p="p" t="6" id="23" x="41.57824694" y="50.29971883" />
<nu p="p" t="6.089804314" id="19" x="41.99780011" y="78.03563217" />
<nu p="p" t="6.25" id="4" x="110.5" y="50" />
<nu p="p" t="6.25" id="8" x="76.90143125" y="79.01519914" />
<nu p="p" t="6.25" id="9" x="105.6240865" y="52.33120214" />
<nu p="p" t="6.25" id="10" x="79.61365279" y="55.15767225" />
<nu p="p" t="6.25" id="14" x="81.98727513" y="59.09829905" />
<nu p="p" t="6.25" id="15" x="107.2488447" y="50.66877601" />
<nu p="p" t="6.25" id="16" x="58.55661784" y="56.00207415" />
<nu p="p" t="6.25" id="17" x="62.20713896" y="72.0630701" />
<nu p="p" t="6.25" id="18" x="49.07582834" y="81.40029911" />
<nu p="p" t="6.25" id="19" x="40.20896318" y="76.95460216" />
<nu p="p" t="6.25" id="20" x="42.771718" y="52.75481298" />
<nu p="p" t="6.25" id="21" x="66.11406543" y="67.68611954" />
<nu p="p" t="6.25" id="22" x="39.57717888" y="70.13418387" />
<nu p="p" t="6.25" id="23" x="40.06841943" y="49.02684023" />
<nu p="p" t="6.5" id="4" x="113" y="50" />
<nu p="p" t="6.5" id="8" x="76.53097872" y="78.13464244" />
<nu p="p" t="6.5" id="9" x="105.6707623" y="53.10568529" />
<nu p="p" t="6.5" id="10" x="80.3052255" y="55.16218973" />
<nu p="p" t="6.5" id="11" x="76.89000268" y="53.78160049" />
<nu p="p" t="6.5" id="12" x="72.86703813" y="74.52326657" />
<nu p="p" t="6.5" id="13" x="76.98242072" y="55.27186324" />
<nu p="p" t="6.5" id="14" x="82.18508672" y="59.82504985" />
<nu p="p" t="6.5" id="15" x="108.1403113" y="50.38518727" />
<nu p="p" t="6.5" id="16" x="57.36413778" y="56.16763313" />
<nu p="p" t="6.5" id="17" x="60.66113535" y="71.1498938" />
<nu p="p" t="6.5" id="18" x="50.41674295" y="80.3374803" />
<nu p="p" t="6.5" id="19" x="37.41731976" y="75.26755607" />
<nu p="p" t="6.5" id="21" x="67.80513419" y="68.05033997" />
<nu p="p" t="6.5" id="22" x="38.24754203" y="71.65718517" />
<nu p="p" t="6.5" id="23" x="38.55859191" y="47.75396163" />
<nu p="p" t="6.519401855" id="17" x="60.541154" y="71.07902454" />
<nu p="p" t="6.716478199" id="19" x="35" y="73.80672129" />
<nu p="p" t="6.75" id="4" x="115.5" y="50" />
<nu p="p" t="6.75" id="8" x="76.16052619" y="77.25408574" />
<nu p="p" t="6.75" id="11" x="77.79850738" y="53.83389563" />
<nu p="p" t="6.75" id="14" x="82.38289831" y="60.55180066" />
<nu p="p" t="6.75" id="15" x="109.031778" y="50.10159853" />
<nu p="p" t="6.75" id="16" x="56.17165772" y="56.33319211" />
<nu p="p" t="6.75" id="17" x="61.29371896" y="71.25034236" />
<nu p="p" t="6.75" id="18" x="51.75765756" y="79.27466149" />
<nu p="p" t="6.75" id="19" x="35.37432366" y="73.58050999" />
<nu p="p" t="6.75" id="20" x="42.05589492" y="51.96196001" />
<nu p="p" t="6.75" id="21" x="69.49620296" y="68.4145604" />
<nu p="p" t="6.75" id="22" x="36.91790517" y="73.18018648" />
<nu p="p" t="6.75" id="23" x="37.0487644" y="46.48108302" />
<nu p="p" t="7" id="4" x="118" y="50" />
<nu p="p" t="7" id="8" x="75.79007366" y="76.37352904" />
<nu p="p" t="7" id="9" x="105.7641137" y="54.65465159" />
<nu p="p" t="7" id="10" x="81.68837093" y="55.17122469" />
<nu p="p" t="7" id="11" x="78.70701208" y="53.88619076" />
<nu p="p" t="7" id="12" x="72.33568715" y="73.54891306" />
<nu p="p" t="7" id="13" x="76.72877177" y="56.41781463" />
<nu p="p" t="7" id="14" x="82.5807099" y="61.27855146" />
<nu p="p" t="7" id="15" x="109.9232446" y="49.81800979" />
<nu p="p" t="7" id="16" x="54.97917767" y="56.49875109" />
<nu p="p" t="7" id="17" x="62.10960254" y="71.43607437" />
<nu p="p" t="7" id="18" x="53.09857217" y="78.21184268" />
<nu p="p" t="7" id="19" x="38.16596708" y="71.89346391" />
<nu p="p" t="7" id="20" x="41.69798338" y="51.56553352" />
<nu p="p" t="7" id="21" x="71.18727172" y="68.77878083" />
<nu p="p" t="7" id="22" x="35.58826832" y="74.70318779" />
<nu p="p" t="7" id="23" x="35.53893688" y="45.20820442" />
<nu p="p" t="7.021525029" id="15" x="110" y="49.79359276" />
<nu p="p" t="7.040892435" id="23" x="35.29197479" y="45" />
<nu p="p" t="7.089238154" id="23" x="35" y="45.24615292" />
<nu p="p" t="7.110606953" id="22" x="35" y="75.37700593" />
<nu p="p" t="7.25" id="4" x="120.5" y="50" />
<nu p="p" t="7.25" id="8" x="75.41962113" y="75.49297234" />
<nu p="p" t="7.25" id="9" x="105.8107895" y="55.42913474" />
<nu p="p" t="7.25" id="10" x="82.37994365" y="55.17574217" />
<nu p="p" t="7.25" id="11" x="79.61551678" y="53.9384859" />
<nu p="p" t="7.25" id="14" x="82.77852149" y="62.00530227" />
<nu p="p" t="7.25" id="16" x="53.78669761" y="56.66431008" />
<nu p="p" t="7.25" id="18" x="54.43948679" y="77.14902387" />
<nu p="p" t="7.25" id="19" x="40.95761051" y="70.20641783" />
<nu p="p" t="7.25" id="21" x="72.87834049" y="69.14300126" />
<nu p="p" t="7.25" id="22" x="35.74136853" y="76.2261891" />
<nu p="p" t="7.25" id="23" x="35.97089063" y="46.06467418" />
<nu p="p" t="7.5" id="4" x="123" y="50" />
<nu p="p" t="7.5" id="8" x="75.0491686" y="74.61241564" />
<nu p="p" t="7.5" id="9" x="105.8574652" y="56.20361789" />
<nu p="p" t="7.5" id="10" x="83.07151636" y="55.18025965" />
<nu p="p" t="7.5" id="11" x="80.52402148" y="53.99078103" />
<nu p="p" t="7.5" id="12" x="71.80433616" y="72.57455956" />
<nu p="p" t="7.5" id="13" x="76.47512281" y="57.56376603" />
<nu p="p" t="7.5" id="15" x="108.2938221" y="49.2508323" />
<nu p="p" t="7.5" id="16" x="52.59421755" y="56.82986906" />
<nu p="p" t="7.5" id="17" x="63.74136971" y="71.80753837" />
<nu p="p" t="7.5" id="18" x="55.7804014" y="76.08620506" />
<nu p="p" t="7.5" id="19" x="43.74925393" y="68.51937175" />
<nu p="p" t="7.5" id="20" x="40.98216031" y="50.77268055" />
<nu p="p" t="7.5" id="21" x="74.56940925" y="69.50722169" />
<nu p="p" t="7.5" id="22" x="37.07100538" y="77.74919041" />
<nu p="p" t="7.5" id="23" x="37.48071815" y="47.33755278" />
<nu p="p" t="7.5636566" id="21" x="75" y="69.59996183" />
<nu p="p" t="7.623458479" id="21" x="74.59548364" y="69.6870861" />
<nu p="p" t="7.75" id="4" x="125.5" y="50" />
<nu p="p" t="7.75" id="8" x="74.67871607" y="73.73185894" />
<nu p="p" t="7.75" id="11" x="81.43252618" y="54.04307617" />
<nu p="p" t="7.75" id="13" x="76.34829834" y="58.13674173" />
<nu p="p" t="7.75" id="14" x="83.17414466" y="63.45880388" />
<nu p="p" t="7.75" id="15" x="107.4023554" y="48.96724356" />
<nu p="p" t="7.75" id="16" x="51.40173749" y="56.99542804" />
<nu p="p" t="7.75" id="17" x="64.55725329" y="71.99327038" />
<nu p="p" t="7.75" id="18" x="57.12131601" y="75.02338625" />
<nu p="p" t="7.75" id="19" x="46.54089735" y="66.83232567" />
<nu p="p" t="7.75" id="21" x="74.23441722" y="71.13071345" />
<nu p="p" t="7.75" id="22" x="38.40064223" y="79.27219171" />
<nu p="p" t="7.75" id="23" x="38.99054567" y="48.61043139" />
<nu p="p" t="7.850863368" id="8" x="74.52925571" y="73.37659528" />
<nu p="p" t="8" id="4" x="128" y="50" />
<nu p="p" t="8" id="9" x="105.9508166" y="57.75258419" />
<nu p="p" t="8" id="10" x="84.45466179" y="55.18929461" />
<nu p="p" t="8" id="11" x="82.34103088" y="54.0953713" />
<nu p="p" t="8" id="12" x="71.27298518" y="71.60020606" />
<nu p="p" t="8" id="14" x="83.37195625" y="64.18555468" />
<nu p="p" t="8" id="15" x="106.5108888" y="48.68365482" />
<nu p="p" t="8" id="16" x="50.20925743" y="57.16098702" />
<nu p="p" t="8" id="17" x="65.373136